testbench/test.sv
module test (
    input clk,
    input rst,
    input [2:0] in,
    output reg [2:0] out
);

    // dff
    reg [2:0] dff_q;

    always @(posedge clk or posedge rst) begin
        if (rst) begin
            dff_q <= 1'b0;
        end else begin
            dff_q <= in;
        end
    end

    always @(posedge clk or posedge rst) begin
        if (rst) begin
            out <= 1'b0;
        end else begin
            out <= dff_q;
        end
    end
    
endmodule

testbench/tb_test.sv
`include "test.sv"
module tb_test (

);
    reg clk;
    reg rstn;
    reg [2:0] in;
    wire [2:0] out;

    always begin
        #5 clk = ~clk;
    end

    initial begin
        // Initialize Inputs
        clk = 0;
        rstn = 1;
        #10 rstn = 0;
        #10 in = 3'b010;
        #10 in = 3'b011;
        #200;
        $finish;
    end

    test DUT (
        .clk(clk),
        .rst(rstn),
        .in(in),
        .out(out)
    );

    // dump waveforms
    initial begin
        $dumpfile("tb_test.vcd");
        $dumpvars(0, tb_test);
    end

endmodule

testbench/tb_test.vcd
$date
	Thu Mar 27 14:30:53 2025
$end
$version
	Icarus Verilog
$end
$timescale
	1s
$end
$scope module tb_test $end
$var wire 3 ! out [2:0] $end
$var reg 1 " clk $end
$var reg 3 # in [2:0] $end
$var reg 1 $ rstn $end
$scope module DUT $end
$var wire 1 " clk $end
$var wire 3 % in [2:0] $end
$var wire 1 $ rst $end
$var reg 3 & dff_q [2:0] $end
$var reg 3 ' out [2:0] $end
$upscope $end
$upscope $end
$enddefinitions $end
$comment Show the parameter values. $end
$dumpall
$end
#0
$dumpvars
b0 '
b0 &
bx %
1$
bx #
0"
b0 !
$end
#5
1"
#10
0"
0$
#15
bx &
1"
#20
0"
b10 #
b10 %
#25
bx !
bx '
b10 &
1"
#30
0"
b11 #
b11 %
#35
b11 &
b10 !
b10 '
1"
#40
0"
#45
b11 !
b11 '
1"
